textshot/logger.py
textshot/messages.py
textshot/notifications.py
textshot/ocr.py
textshot/textshot.py
textshot-0.1.2.dist-info/LICENSE.txt
textshot-0.1.2.dist-info/METADATA
textshot-0.1.2.dist-info/WHEEL
textshot-0.1.2.dist-info/entry_points.txt
textshot-0.1.2.dist-info/top_level.txt
textshot-0.1.2.dist-info/RECORD
