Metadata-Version: 2.1
Name: textshot
Version: 0.1.2
Summary: Python tool for grabbing text via screenshot
Author-email: Ian Zhao <ian.z05@outlook.com>
Project-URL: Homepage, https://github.com/ianzhao05/textshot
Project-URL: Bug Tracker, https://github.com/ianzhao05/textshot/issues/
Classifier: Programming Language :: Python :: 3
Classifier: License :: OSI Approved :: MIT License
Classifier: Operating System :: OS Independent
Requires-Python: >=3.7
License-File: LICENSE.txt
Requires-Dist: Pillow~=9.4.0
Requires-Dist: PyQt5~=5.15.7
Requires-Dist: PyQt5-sip~=12.11.0
Requires-Dist: PyQt5-stubs~=5.15.6.0
Requires-Dist: py-notifier==0.3.2
Requires-Dist: pyperclip~=1.8.2
Requires-Dist: pytesseract~=0.3.10
Requires-Dist: win10toast~=0.9; platform_system == "Windows"
